ScanCE/Scan_ce_loose.py
ScanCE/Scan_ce_strict.py
ScanCE/__init__.py
ScanCE/__main__.py
ScanCE-1.1.dist-info/AUTHORS.rst
ScanCE-1.1.dist-info/LICENSE
ScanCE-1.1.dist-info/METADATA
ScanCE-1.1.dist-info/WHEEL
ScanCE-1.1.dist-info/entry_points.txt
ScanCE-1.1.dist-info/top_level.txt
ScanCE-1.1.dist-info/RECORD
