Metadata-Version: 2.1
Name: ScanCE
Version: 1.1
Summary: A computational workflow for cryptic exon identification in RNA-seq data.
Home-page: https://github.com/lu000016/ScanCE
Author: Xiaotong Lu
Author-email: lu000016@umn.edu
License: MIT license
Classifier: Development Status :: 2 - Pre-Alpha
Classifier: Intended Audience :: Developers
Classifier: License :: OSI Approved :: MIT License
Classifier: Natural Language :: English
Classifier: Programming Language :: Python :: 3.7
Classifier: Programming Language :: Python :: 3.8
Requires-Python: >=3.7
License-File: LICENSE
License-File: AUTHORS.rst
Requires-Dist: pysam
Requires-Dist: gffutils
Requires-Dist: pandas
Requires-Dist: biopython
Requires-Dist: numpy
Requires-Dist: scipy
